aidkit/__init__.py
aidkit/config.py
aidkit/analysis/__init__.py
aidkit/analysis/__main__.py
aidkit/analysis/comprehensibility/__init__.py
aidkit/analysis/comprehensibility/gradient_map.py
aidkit/analysis/functionality/__init__.py
aidkit/analysis/functionality/performance.py
aidkit/analysis/robustness/__init__.py
aidkit/authenticate/__init__.py
aidkit/authenticate/__main__.py
aidkit/core/__init__.py
aidkit/core/request_model.py
aidkit/core/stored_model.py
aidkit/core/utils.py
aidkit/core/analyses/__init__.py
aidkit/core/analyses/aggregated_constant.py
aidkit/core/analyses/aggregated_relative_constant.py
aidkit/core/analyses/blackbox.py
aidkit/core/analyses/constant.py
aidkit/core/analyses/correlation.py
aidkit/core/analyses/data_investigation.py
aidkit/core/analyses/fgsm.py
aidkit/core/analyses/gradient_map.py
aidkit/core/analyses/inc_dec.py
aidkit/core/analyses/kri.py
aidkit/core/analyses/peak.py
aidkit/core/analyses/performance.py
aidkit/core/analyses/random.py
aidkit/core/analyses/relative_constant.py
aidkit/data/__init__.py
aidkit/data/__main__.py
aidkit/data_access/__init__.py
aidkit/data_access/analysis.py
aidkit/data_access/api.py
aidkit/data_access/authentication.py
aidkit/data_access/data.py
aidkit/data_access/model.py
aidkit/data_access/stored_model_access.py
aidkit/data_access/utils.py
aidkit/model/__init__.py
aidkit/model/__main__.py
aidkit/report/__init__.py
aidkit/report/__main__.py
aidkit-0.2.5.dist-info/METADATA
aidkit-0.2.5.dist-info/WHEEL
aidkit-0.2.5.dist-info/top_level.txt
aidkit-0.2.5.dist-info/RECORD
