Metadata-Version: 2.1
Name: aidkit
Version: 0.2.5
Summary: aidkit, the first aid kit for AI development, verification & validation. The AI-debugging &-boosting toolkit is both the embodiment of quality standards, as well as the plug & play tool for AI developers who want to put their model through its paces in every section of the AI lifecycle to reduce costs / iterations. 
Home-page: https://aidkit.ai/
Author: neurocat GmbH
Author-email: dev@neurocat.ai
License: GNU AGPLv3
Platform: UNKNOWN
Requires-Dist: pytest (==6.1.0)
Requires-Dist: requests (==2.24.0)
